prototwin_cmdbuff.cpython-39-darwin.so
prototwin_cmdbuff-1.1.0.dist-info/RECORD
prototwin_cmdbuff-1.1.0.dist-info/WHEEL
prototwin_cmdbuff-1.1.0.dist-info/top_level.txt
prototwin_cmdbuff-1.1.0.dist-info/METADATA
