Metadata-Version: 2.4
Name: prototwin_cmdbuff
Version: 1.1.0
Summary: Optimized command buffer for the ProtoTwin Connect client.
Dynamic: description
Dynamic: description-content-type
Dynamic: summary
